chaichai/__init__.py
chaichai/pdfTools.py
chaichai/rabbitmq.py
chaichai-0.0.4.dist-info/METADATA
chaichai-0.0.4.dist-info/WHEEL
chaichai-0.0.4.dist-info/top_level.txt
chaichai-0.0.4.dist-info/RECORD
