Metadata-Version: 2.2
Name: chaichai
Version: 0.0.4
Summary: A powerful tool library
Home-page: https://github.com/starry/chaichai
Author: Starry
Author-email: uifox_starry@163.com
License: Apache-2.0
Keywords: rpa,windows,rabbitmq,automation
Requires-Dist: pika~=1.3.1
Requires-Dist: pdfminer.six>=20221105
Dynamic: author
Dynamic: author-email
Dynamic: description-content-type
Dynamic: home-page
Dynamic: keywords
Dynamic: license
Dynamic: requires-dist
Dynamic: summary
